{
  "version": "loupe-ir/v1", "root": "model",
  "provenance": { "source": "hand-authored", "generated_at": "2026-06-29", "generator": "loupe lstm" },
  "lod_policy": { "bands": 3, "distance_thresholds": [8.0, 3.6] },
  "entities": [
    { "id": "model", "label": "LSTM", "kind": "model", "parent": null, "lod_band": 0, "placement": { "pos": [0,1.8,2.0] }, "payload": { "type": "text", "data": { "accent": [0.5,0.85,1.0], "width": 2.0, "height": 1.0 } }, "content_tiers": { "overview": "Recurrent net: reads a sequence step by step", "detail": "hidden + cell state carried across time", "deep": "gates control what to keep, add, output" } },
    { "id": "emb", "label": "Embeddings", "kind": "input", "parent": "model", "lod_band": 1, "placement": { "pos": [0,0,1.6] }, "payload": { "type": "matrix", "data": { "rows": 30000, "cols": 256, "accent": [0.5,0.9,0.7], "eqn": "embed" } }, "content_tiers": { "overview": "Token to 256-d vector" } },
    { "id": "t1", "label": "Cell t-1", "kind": "block", "parent": "model", "lod_band": 1, "placement": { "pos": [0,0,0.4], "scale": [0.85,0.85,0.85] }, "payload": { "type": "text", "data": { "accent": [0.4,0.8,1.0], "width": 1.2, "height": 0.8 } }, "content_tiers": { "overview": "Step t-1: shared weights" } },
    { "id": "t2", "label": "Cell t", "kind": "block", "parent": "model", "lod_band": 1, "placement": { "pos": [0,0,-0.8], "scale": [0.85,0.85,0.85] }, "payload": { "type": "text", "data": { "accent": [0.5,0.9,1.0], "width": 1.2, "height": 0.8 } }, "content_tiers": { "overview": "Dive: highway, 3 gates, pointwise ops" } },
    { "id": "t3", "label": "Cell t+1", "kind": "block", "parent": "model", "lod_band": 1, "placement": { "pos": [0,0,-2.0], "scale": [0.85,0.85,0.85] }, "payload": { "type": "text", "data": { "accent": [0.4,0.8,1.0], "width": 1.2, "height": 0.8 } }, "content_tiers": { "overview": "Step t+1" } },
    { "id": "out", "label": "Output", "kind": "output", "parent": "model", "lod_band": 1, "placement": { "pos": [0,0,-3.2] }, "payload": { "type": "matrix", "data": { "rows": 256, "cols": 30000, "accent": [0.95,0.7,0.4], "eqn": "softmax" } }, "content_tiers": { "overview": "Hidden to vocab; softmax" } },
    { "id": "boundary", "label": "", "kind": "frame", "parent": "t2", "lod_band": 2, "placement": { "pos": [0,0,0.05] }, "payload": { "type": "graph", "data": { "raw": true, "edge_color": [0.45,0.75,1.0,0.55], "node_radius": 0.001, "nodes": [{"pos":[-3.4,1.9,0]},{"pos":[3.4,1.9,0]},{"pos":[3.4,-1.3,0]},{"pos":[-3.4,-1.3,0]},{"pos":[-3,1.4,0]},{"pos":[-1.4,1.4,0]},{"pos":[0.6,1.4,0]},{"pos":[3,1.4,0]},{"pos":[-1.4,-0.4,0]},{"pos":[0.6,-0.4,0]},{"pos":[2.4,-0.4,0]},{"pos":[2.4,1.4,0]}], "edges": [[0,1],[1,2],[2,3],[3,0],[4,5],[5,6],[6,7],[8,5],[9,6],[10,11]] } }, "content_tiers": {} },
    { "id": "cin", "label": "c(t-1)", "kind": "input", "parent": "t2", "lod_band": 2, "placement": { "pos": [-3,1.4,0], "scale": [0.4,0.4,0.4] }, "payload": { "type": "text", "data": { "accent": [1.0,0.9,0.5], "width": 0.9, "height": 0.4 } }, "content_tiers": { "overview": "Cell state in (memory highway)" } },
    { "id": "mf", "label": "x", "kind": "op", "parent": "t2", "lod_band": 2, "placement": { "pos": [-1.4,1.4,0], "scale": [0.35,0.35,0.35] }, "payload": { "type": "text", "data": { "accent": [1.0,0.6,0.6], "width": 0.5, "height": 0.5 } }, "content_tiers": { "overview": "Forget scales old memory" } },
    { "id": "add", "label": "+", "kind": "op", "parent": "t2", "lod_band": 2, "placement": { "pos": [0.6,1.4,0], "scale": [0.35,0.35,0.35] }, "payload": { "type": "text", "data": { "accent": [0.6,1.0,0.7], "width": 0.5, "height": 0.5 } }, "content_tiers": { "overview": "Add new candidate" } },
    { "id": "cout", "label": "c(t)", "kind": "output", "parent": "t2", "lod_band": 2, "placement": { "pos": [3,1.4,0], "scale": [0.4,0.4,0.4] }, "payload": { "type": "text", "data": { "accent": [1.0,0.9,0.5], "width": 0.9, "height": 0.4 } }, "content_tiers": { "overview": "Cell state out" } },
    { "id": "fgate", "label": "forget sigma", "kind": "head", "parent": "t2", "lod_band": 2, "placement": { "pos": [-1.4,-0.4,0], "scale": [0.5,0.5,0.5] }, "payload": { "type": "text", "data": { "accent": [1.0,0.6,0.6], "width": 1.0, "height": 0.5, "eqn": "lstm_f" } }, "content_tiers": { "overview": "Fraction of memory to keep" } },
    { "id": "igate", "label": "input + candidate", "kind": "head", "parent": "t2", "lod_band": 2, "placement": { "pos": [0.6,-0.4,0], "scale": [0.5,0.5,0.5] }, "payload": { "type": "text", "data": { "accent": [0.6,1.0,0.7], "width": 1.0, "height": 0.5, "eqn": "lstm_c" } }, "content_tiers": { "overview": "What new info to write" } },
    { "id": "ogate", "label": "output gate", "kind": "head", "parent": "t2", "lod_band": 2, "placement": { "pos": [2.4,-0.4,0], "scale": [0.5,0.5,0.5] }, "payload": { "type": "text", "data": { "accent": [0.6,0.85,1.0], "width": 1.0, "height": 0.5, "eqn": "lstm_o" } }, "content_tiers": { "overview": "Reveal memory as h(t)" } }
  ],
  "relations": [
    { "from": "emb", "to": "t1", "kind": "flow" }, { "from": "t1", "to": "t2", "kind": "flow" }, { "from": "t2", "to": "t3", "kind": "flow" }, { "from": "t3", "to": "out", "kind": "flow" },
    { "from": "cin", "to": "mf", "kind": "flow" }, { "from": "mf", "to": "add", "kind": "flow" }, { "from": "add", "to": "cout", "kind": "flow" }, { "from": "fgate", "to": "mf", "kind": "flow" }, { "from": "igate", "to": "add", "kind": "flow" }, { "from": "add", "to": "ogate", "kind": "flow" }
  ]
}

